convert_thai_to_arabic/__init__.py
convert_thai_to_arabic/convert_thai_to_arabic.py
convert_thai_to_arabic-0.0.7.dist-info/METADATA
convert_thai_to_arabic-0.0.7.dist-info/WHEEL
convert_thai_to_arabic-0.0.7.dist-info/entry_points.txt
convert_thai_to_arabic-0.0.7.dist-info/top_level.txt
convert_thai_to_arabic-0.0.7.dist-info/RECORD
